configargparse.py
ConfigArgParse-1.5.5.dist-info/LICENSE
ConfigArgParse-1.5.5.dist-info/METADATA
ConfigArgParse-1.5.5.dist-info/WHEEL
ConfigArgParse-1.5.5.dist-info/top_level.txt
ConfigArgParse-1.5.5.dist-info/RECORD
