Metadata-Version: 2.1
Name: ConfigArgParse
Version: 1.5.5
Summary: A drop-in replacement for argparse that allows options to also be set via config files and/or environment variables.
Home-page: https://github.com/bw2/ConfigArgParse
License: MIT
Keywords: options,argparse,ConfigArgParse,config,environment variables,envvars,ENV,environment,optparse,YAML,INI
Classifier: Development Status :: 4 - Beta
Classifier: Intended Audience :: Developers
Classifier: License :: OSI Approved :: MIT License
Classifier: Natural Language :: English
Classifier: Programming Language :: Python :: 2
Classifier: Programming Language :: Python :: 2.7
Classifier: Programming Language :: Python :: 3
Classifier: Programming Language :: Python :: 3.5
Classifier: Programming Language :: Python :: 3.6
Classifier: Programming Language :: Python :: 3.7
Classifier: Programming Language :: Python :: 3.8
Classifier: Programming Language :: Python :: 3.9
Classifier: Programming Language :: Python :: 3.10
Classifier: Programming Language :: Python :: Implementation :: CPython
Classifier: Programming Language :: Python :: Implementation :: PyPy
Requires-Python: >=2.7, !=3.0.*, !=3.1.*, !=3.2.*, !=3.3.*, !=3.4.*
Provides-Extra: yaml
Provides-Extra: test
License-File: LICENSE
